[
    {
        "time":"0",
        "truVal":"24",
        "proVal":"24.9534893"
    },
    {
        "time":"1",
        "truVal":"17",
        "proVal":"12.32447433"
    },
    {
        "time":"2",
        "truVal":"6",
        "proVal":"7.9986863139999995"
    },
    {
        "time":"3",
        "truVal":"3",
        "proVal":"6.959486485"
    },
    {
        "time":"4",
        "truVal":"2",
        "proVal":"6.974355221000001"
    },
    {
        "time":"5",
        "truVal":"0",
        "proVal":"7.94194746"
    },
    {
        "time":"6",
        "truVal":"11",
        "proVal":"11.56666851"
    },
    {
        "time":"7",
        "truVal":"16",
        "proVal":"20.34805298"
    },
    {
        "time":"8",
        "truVal":"58",
        "proVal":"27.01904106"
    },
    {
        "time":"9",
        "truVal":"46",
        "proVal":"55.32097626"
    },
    {
        "time":"10",
        "truVal":"48",
        "proVal":"68.22360229"
    },
    {
        "time":"11",
        "truVal":"62",
        "proVal":"78.04335022"
    },
    {
        "time":"12",
        "truVal":"99",
        "proVal":"85.02212524"
    },
    {
        "time":"13",
        "truVal":"99",
        "proVal":"99.70698547"
    },
    {
        "time":"14",
        "truVal":"99",
        "proVal":"100.6480026"
    },
    {
        "time":"15",
        "truVal":"137",
        "proVal":"105.7015686"
    },
    {
        "time":"16",
        "truVal":"143",
        "proVal":"133.9384003"
    },
    {
        "time":"17",
        "truVal":"161",
        "proVal":"138.5542755"
    },
    {
        "time":"18",
        "truVal":"186",
        "proVal":"144.9924469"
    },
    {
        "time":"19",
        "truVal":"134",
        "proVal":"152.8389435"
    },
    {
        "time":"20",
        "truVal":"121",
        "proVal":"114.0581818"
    },
    {
        "time":"21",
        "truVal":"224",
        "proVal":"127.4935303"
    },
    {
        "time":"22",
        "truVal":"235",
        "proVal":"187.6078644"
    },
    {
        "time":"23",
        "truVal":"125",
        "proVal":"112.9800644"
    }
]