[
    {
        "lng": 110.2504,
        "lat": 20.0127,
        "count": 1
    },
    {
        "lng": 110.2604,
        "lat": 20.0112,
        "count": 1
    },
    {
        "lng": 110.2606,
        "lat": 20.0112,
        "count": 1
    },
    {
        "lng": 110.2616,
        "lat": 20.0004,
        "count": 1
    },
    {
        "lng": 110.2688,
        "lat": 20.0151,
        "count": 1
    },
    {
        "lng": 110.2803,
        "lat": 20.0134,
        "count": 1
    },
    {
        "lng": 110.2815,
        "lat": 20.0134,
        "count": 1
    },
    {
        "lng": 110.2825,
        "lat": 20.0135,
        "count": 1
    },
    {
        "lng": 110.2828,
        "lat": 20.0136,
        "count": 1
    },
    {
        "lng": 110.2843,
        "lat": 19.9997,
        "count": 1
    },
    {
        "lng": 110.2844,
        "lat": 19.9995,
        "count": 1
    },
    {
        "lng": 110.2846,
        "lat": 19.99,
        "count": 1
    },
    {
        "lng": 110.2846,
        "lat": 19.9909,
        "count": 1
    },
    {
        "lng": 110.2851,
        "lat": 20.0213,
        "count": 1
    },
    {
        "lng": 110.2875,
        "lat": 19.9987,
        "count": 1
    },
    {
        "lng": 110.2876,
        "lat": 20.0252,
        "count": 1
    },
    {
        "lng": 110.2879,
        "lat": 20.0154,
        "count": 1
    },
    {
        "lng": 110.2882,
        "lat": 20.0104,
        "count": 1
    },
    {
        "lng": 110.2889,
        "lat": 19.9965,
        "count": 1
    },
    {
        "lng": 110.2911,
        "lat": 20.0155,
        "count": 1
    },
    {
        "lng": 110.2938,
        "lat": 20.0267,
        "count": 1
    },
    {
        "lng": 110.2939,
        "lat": 20.0227,
        "count": 1
    },
    {
        "lng": 110.2944,
        "lat": 19.9985,
        "count": 1
    },
    {
        "lng": 110.2944,
        "lat": 20.0182,
        "count": 1
    },
    {
        "lng": 110.2965,
        "lat": 20.0266,
        "count": 1
    },
    {
        "lng": 110.2978,
        "lat": 20.0254,
        "count": 1
    },
    {
        "lng": 110.2998,
        "lat": 20.0172,
        "count": 1
    },
    {
        "lng": 110.2999,
        "lat": 20.0215,
        "count": 1
    },
    {
        "lng": 110.3007,
        "lat": 20.0172,
        "count": 1
    },
    {
        "lng": 110.3014,
        "lat": 19.9646,
        "count": 2
    },
    {
        "lng": 110.3022,
        "lat": 19.9997,
        "count": 1
    },
    {
        "lng": 110.3023,
        "lat": 20.0027,
        "count": 1
    },
    {
        "lng": 110.3024,
        "lat": 19.9987,
        "count": 1
    },
    {
        "lng": 110.305,
        "lat": 19.9967,
        "count": 1
    },
    {
        "lng": 110.3054,
        "lat": 19.9994,
        "count": 1
    },
    {
        "lng": 110.3063,
        "lat": 20.0207,
        "count": 1
    },
    {
        "lng": 110.3068,
        "lat": 20.02,
        "count": 1
    },
    {
        "lng": 110.307,
        "lat": 20.0124,
        "count": 1
    },
    {
        "lng": 110.307,
        "lat": 20.0148,
        "count": 2
    },
    {
        "lng": 110.3071,
        "lat": 20.0124,
        "count": 2
    },
    {
        "lng": 110.3072,
        "lat": 20.0078,
        "count": 1
    },
    {
        "lng": 110.3089,
        "lat": 20.0027,
        "count": 1
    },
    {
        "lng": 110.3099,
        "lat": 20.015,
        "count": 1
    },
    {
        "lng": 110.31,
        "lat": 20.017,
        "count": 2
    },
    {
        "lng": 110.3114,
        "lat": 20.0195,
        "count": 1
    },
    {
        "lng": 110.3121,
        "lat": 20.0252,
        "count": 3
    },
    {
        "lng": 110.3132,
        "lat": 20.0167,
        "count": 3
    },
    {
        "lng": 110.3135,
        "lat": 19.9968,
        "count": 1
    },
    {
        "lng": 110.3146,
        "lat": 19.9917,
        "count": 1
    },
    {
        "lng": 110.315,
        "lat": 19.9842,
        "count": 1
    },
    {
        "lng": 110.3153,
        "lat": 20.0297,
        "count": 1
    },
    {
        "lng": 110.3154,
        "lat": 20.0155,
        "count": 1
    },
    {
        "lng": 110.3154,
        "lat": 20.0297,
        "count": 1
    },
    {
        "lng": 110.3161,
        "lat": 20.0551,
        "count": 1
    },
    {
        "lng": 110.3168,
        "lat": 20.0303,
        "count": 1
    },
    {
        "lng": 110.3173,
        "lat": 20.0261,
        "count": 1
    },
    {
        "lng": 110.3174,
        "lat": 20.0226,
        "count": 3
    },
    {
        "lng": 110.3176,
        "lat": 20.0238,
        "count": 1
    },
    {
        "lng": 110.3177,
        "lat": 20.0229,
        "count": 2
    },
    {
        "lng": 110.3179,
        "lat": 19.9931,
        "count": 1
    },
    {
        "lng": 110.3184,
        "lat": 19.9913,
        "count": 1
    },
    {
        "lng": 110.3187,
        "lat": 20.0322,
        "count": 1
    },
    {
        "lng": 110.3194,
        "lat": 20.0256,
        "count": 1
    },
    {
        "lng": 110.3195,
        "lat": 20.0392,
        "count": 2
    },
    {
        "lng": 110.3198,
        "lat": 20.0396,
        "count": 4
    },
    {
        "lng": 110.3201,
        "lat": 20.0279,
        "count": 1
    },
    {
        "lng": 110.3205,
        "lat": 20.026,
        "count": 1
    },
    {
        "lng": 110.3206,
        "lat": 20.0154,
        "count": 1
    },
    {
        "lng": 110.3208,
        "lat": 20.0247,
        "count": 1
    },
    {
        "lng": 110.3209,
        "lat": 20.0163,
        "count": 1
    },
    {
        "lng": 110.3213,
        "lat": 20.0264,
        "count": 1
    },
    {
        "lng": 110.3218,
        "lat": 20.0268,
        "count": 1
    },
    {
        "lng": 110.3219,
        "lat": 20.0265,
        "count": 1
    },
    {
        "lng": 110.322,
        "lat": 20.0221,
        "count": 1
    },
    {
        "lng": 110.322,
        "lat": 20.0279,
        "count": 1
    },
    {
        "lng": 110.3226,
        "lat": 19.9817,
        "count": 1
    },
    {
        "lng": 110.3236,
        "lat": 20.0106,
        "count": 1
    },
    {
        "lng": 110.3236,
        "lat": 20.0281,
        "count": 1
    },
    {
        "lng": 110.3242,
        "lat": 20.0107,
        "count": 1
    },
    {
        "lng": 110.3242,
        "lat": 20.0617,
        "count": 1
    },
    {
        "lng": 110.3243,
        "lat": 20.0028,
        "count": 1
    },
    {
        "lng": 110.3246,
        "lat": 20.0282,
        "count": 1
    },
    {
        "lng": 110.3256,
        "lat": 20.0258,
        "count": 1
    },
    {
        "lng": 110.3256,
        "lat": 20.0262,
        "count": 1
    },
    {
        "lng": 110.3256,
        "lat": 20.029,
        "count": 1
    },
    {
        "lng": 110.3258,
        "lat": 20.0293,
        "count": 1
    },
    {
        "lng": 110.3259,
        "lat": 20.0292,
        "count": 1
    },
    {
        "lng": 110.3259,
        "lat": 20.0293,
        "count": 2
    },
    {
        "lng": 110.3262,
        "lat": 20.039,
        "count": 1
    },
    {
        "lng": 110.3264,
        "lat": 20.03,
        "count": 1
    },
    {
        "lng": 110.3265,
        "lat": 19.9969,
        "count": 1
    },
    {
        "lng": 110.3265,
        "lat": 20.0297,
        "count": 1
    },
    {
        "lng": 110.3266,
        "lat": 20.0198,
        "count": 1
    },
    {
        "lng": 110.3267,
        "lat": 20.0198,
        "count": 1
    },
    {
        "lng": 110.3268,
        "lat": 19.9975,
        "count": 1
    },
    {
        "lng": 110.3269,
        "lat": 20.0196,
        "count": 1
    },
    {
        "lng": 110.3269,
        "lat": 20.0199,
        "count": 1
    },
    {
        "lng": 110.327,
        "lat": 20.0249,
        "count": 1
    },
    {
        "lng": 110.327,
        "lat": 20.0355,
        "count": 1
    },
    {
        "lng": 110.3271,
        "lat": 20.0226,
        "count": 1
    },
    {
        "lng": 110.3272,
        "lat": 20.0195,
        "count": 1
    },
    {
        "lng": 110.3273,
        "lat": 20.0194,
        "count": 1
    },
    {
        "lng": 110.3285,
        "lat": 19.9968,
        "count": 1
    },
    {
        "lng": 110.3289,
        "lat": 19.9934,
        "count": 1
    },
    {
        "lng": 110.3295,
        "lat": 19.9953,
        "count": 1
    },
    {
        "lng": 110.3297,
        "lat": 20.021,
        "count": 1
    },
    {
        "lng": 110.3298,
        "lat": 20.0216,
        "count": 1
    },
    {
        "lng": 110.3298,
        "lat": 20.0235,
        "count": 1
    },
    {
        "lng": 110.3298,
        "lat": 20.0275,
        "count": 1
    },
    {
        "lng": 110.3301,
        "lat": 20.0417,
        "count": 1
    },
    {
        "lng": 110.3301,
        "lat": 20.0682,
        "count": 1
    },
    {
        "lng": 110.3303,
        "lat": 20.0275,
        "count": 1
    },
    {
        "lng": 110.3309,
        "lat": 20.0224,
        "count": 1
    },
    {
        "lng": 110.3312,
        "lat": 20.0282,
        "count": 1
    },
    {
        "lng": 110.3317,
        "lat": 20.0563,
        "count": 1
    },
    {
        "lng": 110.3319,
        "lat": 20.0411,
        "count": 1
    },
    {
        "lng": 110.3324,
        "lat": 20.0238,
        "count": 1
    },
    {
        "lng": 110.3329,
        "lat": 20.0649,
        "count": 1
    },
    {
        "lng": 110.333,
        "lat": 20.003,
        "count": 1
    },
    {
        "lng": 110.3336,
        "lat": 19.982,
        "count": 1
    },
    {
        "lng": 110.3336,
        "lat": 19.9964,
        "count": 1
    },
    {
        "lng": 110.3337,
        "lat": 19.999,
        "count": 1
    },
    {
        "lng": 110.3337,
        "lat": 20.0263,
        "count": 1
    },
    {
        "lng": 110.3338,
        "lat": 20.0238,
        "count": 1
    },
    {
        "lng": 110.3344,
        "lat": 20.0269,
        "count": 2
    },
    {
        "lng": 110.3349,
        "lat": 20.022,
        "count": 1
    },
    {
        "lng": 110.335,
        "lat": 20.0194,
        "count": 1
    },
    {
        "lng": 110.3353,
        "lat": 20.0272,
        "count": 1
    },
    {
        "lng": 110.3356,
        "lat": 20.031,
        "count": 1
    },
    {
        "lng": 110.3357,
        "lat": 20.024,
        "count": 1
    },
    {
        "lng": 110.3357,
        "lat": 20.0276,
        "count": 1
    },
    {
        "lng": 110.3358,
        "lat": 20.0662,
        "count": 1
    },
    {
        "lng": 110.3361,
        "lat": 19.9943,
        "count": 1
    },
    {
        "lng": 110.3363,
        "lat": 20.0203,
        "count": 1
    },
    {
        "lng": 110.3364,
        "lat": 20.0084,
        "count": 1
    },
    {
        "lng": 110.3365,
        "lat": 19.9995,
        "count": 1
    },
    {
        "lng": 110.3365,
        "lat": 20.0349,
        "count": 1
    },
    {
        "lng": 110.3367,
        "lat": 20.0033,
        "count": 1
    },
    {
        "lng": 110.3367,
        "lat": 20.0211,
        "count": 1
    },
    {
        "lng": 110.3368,
        "lat": 19.9804,
        "count": 1
    },
    {
        "lng": 110.3368,
        "lat": 20.0332,
        "count": 1
    },
    {
        "lng": 110.3371,
        "lat": 20.0683,
        "count": 1
    },
    {
        "lng": 110.338,
        "lat": 20.0106,
        "count": 1
    },
    {
        "lng": 110.3385,
        "lat": 20.0055,
        "count": 1
    },
    {
        "lng": 110.3386,
        "lat": 20.0374,
        "count": 1
    },
    {
        "lng": 110.339,
        "lat": 20.0233,
        "count": 1
    },
    {
        "lng": 110.339,
        "lat": 20.0271,
        "count": 1
    },
    {
        "lng": 110.3391,
        "lat": 20.0049,
        "count": 1
    },
    {
        "lng": 110.3392,
        "lat": 20.0096,
        "count": 1
    },
    {
        "lng": 110.3393,
        "lat": 20.0278,
        "count": 1
    },
    {
        "lng": 110.3393,
        "lat": 20.0392,
        "count": 1
    },
    {
        "lng": 110.3396,
        "lat": 20.0303,
        "count": 1
    },
    {
        "lng": 110.3396,
        "lat": 20.0472,
        "count": 1
    },
    {
        "lng": 110.3397,
        "lat": 20.0304,
        "count": 1
    },
    {
        "lng": 110.34,
        "lat": 19.9853,
        "count": 1
    },
    {
        "lng": 110.34,
        "lat": 20.0031,
        "count": 1
    },
    {
        "lng": 110.3401,
        "lat": 20.033,
        "count": 2
    },
    {
        "lng": 110.3403,
        "lat": 20.0055,
        "count": 1
    },
    {
        "lng": 110.3404,
        "lat": 20.0219,
        "count": 1
    },
    {
        "lng": 110.3404,
        "lat": 20.0601,
        "count": 1
    },
    {
        "lng": 110.3405,
        "lat": 19.9978,
        "count": 1
    },
    {
        "lng": 110.3405,
        "lat": 20.0014,
        "count": 1
    },
    {
        "lng": 110.3406,
        "lat": 20.0296,
        "count": 1
    },
    {
        "lng": 110.3407,
        "lat": 20.054,
        "count": 1
    },
    {
        "lng": 110.3409,
        "lat": 19.9961,
        "count": 1
    },
    {
        "lng": 110.3409,
        "lat": 20.0288,
        "count": 1
    },
    {
        "lng": 110.341,
        "lat": 20.0222,
        "count": 1
    },
    {
        "lng": 110.341,
        "lat": 20.0354,
        "count": 1
    },
    {
        "lng": 110.3411,
        "lat": 19.9967,
        "count": 1
    },
    {
        "lng": 110.3412,
        "lat": 20.047,
        "count": 1
    },
    {
        "lng": 110.3416,
        "lat": 20.0496,
        "count": 1
    },
    {
        "lng": 110.342,
        "lat": 19.9817,
        "count": 2
    },
    {
        "lng": 110.3422,
        "lat": 20.0243,
        "count": 1
    },
    {
        "lng": 110.3425,
        "lat": 20.0006,
        "count": 1
    },
    {
        "lng": 110.3427,
        "lat": 20.0553,
        "count": 1
    },
    {
        "lng": 110.343,
        "lat": 20.0113,
        "count": 1
    },
    {
        "lng": 110.3435,
        "lat": 20.0523,
        "count": 1
    },
    {
        "lng": 110.3442,
        "lat": 20.0525,
        "count": 1
    },
    {
        "lng": 110.3446,
        "lat": 19.9834,
        "count": 1
    },
    {
        "lng": 110.3447,
        "lat": 19.9835,
        "count": 1
    },
    {
        "lng": 110.3452,
        "lat": 20.0528,
        "count": 1
    },
    {
        "lng": 110.3459,
        "lat": 20.0204,
        "count": 1
    },
    {
        "lng": 110.3466,
        "lat": 20.0171,
        "count": 1
    },
    {
        "lng": 110.3472,
        "lat": 20.0505,
        "count": 1
    },
    {
        "lng": 110.3476,
        "lat": 20.0348,
        "count": 1
    },
    {
        "lng": 110.3481,
        "lat": 20.0303,
        "count": 1
    },
    {
        "lng": 110.3482,
        "lat": 20.0536,
        "count": 1
    },
    {
        "lng": 110.349,
        "lat": 19.9899,
        "count": 1
    },
    {
        "lng": 110.3494,
        "lat": 19.99,
        "count": 1
    },
    {
        "lng": 110.35,
        "lat": 19.9949,
        "count": 1
    },
    {
        "lng": 110.35,
        "lat": 20.0044,
        "count": 1
    },
    {
        "lng": 110.35,
        "lat": 20.0285,
        "count": 1
    },
    {
        "lng": 110.3502,
        "lat": 19.9948,
        "count": 1
    },
    {
        "lng": 110.3503,
        "lat": 20.0025,
        "count": 1
    },
    {
        "lng": 110.3503,
        "lat": 20.0321,
        "count": 1
    },
    {
        "lng": 110.3504,
        "lat": 20.0307,
        "count": 1
    },
    {
        "lng": 110.3504,
        "lat": 20.0324,
        "count": 1
    },
    {
        "lng": 110.3505,
        "lat": 20.0049,
        "count": 1
    },
    {
        "lng": 110.3508,
        "lat": 19.9899,
        "count": 1
    },
    {
        "lng": 110.3509,
        "lat": 19.9886,
        "count": 1
    },
    {
        "lng": 110.3511,
        "lat": 20.0236,
        "count": 1
    },
    {
        "lng": 110.3514,
        "lat": 19.9901,
        "count": 1
    },
    {
        "lng": 110.3518,
        "lat": 19.9891,
        "count": 1
    },
    {
        "lng": 110.3519,
        "lat": 20.0288,
        "count": 1
    },
    {
        "lng": 110.3522,
        "lat": 20.0317,
        "count": 1
    },
    {
        "lng": 110.3523,
        "lat": 20.068,
        "count": 3
    },
    {
        "lng": 110.3525,
        "lat": 20.054,
        "count": 1
    },
    {
        "lng": 110.3525,
        "lat": 20.0545,
        "count": 1
    },
    {
        "lng": 110.3526,
        "lat": 20.054,
        "count": 1
    },
    {
        "lng": 110.3531,
        "lat": 20.052,
        "count": 1
    },
    {
        "lng": 110.3535,
        "lat": 20.0009,
        "count": 1
    },
    {
        "lng": 110.3537,
        "lat": 20.0438,
        "count": 1
    },
    {
        "lng": 110.3539,
        "lat": 20.0195,
        "count": 1
    },
    {
        "lng": 110.354,
        "lat": 20.0494,
        "count": 1
    },
    {
        "lng": 110.3542,
        "lat": 20.005,
        "count": 1
    },
    {
        "lng": 110.3543,
        "lat": 20.0523,
        "count": 1
    },
    {
        "lng": 110.3547,
        "lat": 20.0207,
        "count": 1
    },
    {
        "lng": 110.3561,
        "lat": 19.9968,
        "count": 1
    },
    {
        "lng": 110.3562,
        "lat": 20.0207,
        "count": 2
    },
    {
        "lng": 110.3565,
        "lat": 19.9987,
        "count": 1
    },
    {
        "lng": 110.3567,
        "lat": 20.0387,
        "count": 1
    },
    {
        "lng": 110.3568,
        "lat": 20.0385,
        "count": 1
    },
    {
        "lng": 110.3568,
        "lat": 20.0387,
        "count": 1
    },
    {
        "lng": 110.3572,
        "lat": 20.0538,
        "count": 1
    },
    {
        "lng": 110.3578,
        "lat": 20.0401,
        "count": 1
    },
    {
        "lng": 110.3592,
        "lat": 20.0463,
        "count": 1
    },
    {
        "lng": 110.3602,
        "lat": 19.9889,
        "count": 1
    },
    {
        "lng": 110.3602,
        "lat": 19.9933,
        "count": 1
    },
    {
        "lng": 110.3615,
        "lat": 19.9911,
        "count": 1
    },
    {
        "lng": 110.3616,
        "lat": 19.991,
        "count": 2
    },
    {
        "lng": 110.3617,
        "lat": 20.0368,
        "count": 1
    },
    {
        "lng": 110.3619,
        "lat": 19.9808,
        "count": 1
    },
    {
        "lng": 110.3629,
        "lat": 19.9974,
        "count": 1
    },
    {
        "lng": 110.3629,
        "lat": 20.0365,
        "count": 1
    },
    {
        "lng": 110.3641,
        "lat": 20.0111,
        "count": 1
    },
    {
        "lng": 110.3646,
        "lat": 19.9888,
        "count": 2
    },
    {
        "lng": 110.3648,
        "lat": 19.9996,
        "count": 1
    },
    {
        "lng": 110.3649,
        "lat": 19.9995,
        "count": 1
    },
    {
        "lng": 110.3665,
        "lat": 20.0083,
        "count": 1
    },
    {
        "lng": 110.3665,
        "lat": 20.0112,
        "count": 1
    },
    {
        "lng": 110.3679,
        "lat": 20.0237,
        "count": 1
    },
    {
        "lng": 110.3691,
        "lat": 20.0274,
        "count": 1
    },
    {
        "lng": 110.3696,
        "lat": 20.0029,
        "count": 1
    },
    {
        "lng": 110.3698,
        "lat": 19.9962,
        "count": 1
    },
    {
        "lng": 110.3699,
        "lat": 20.003,
        "count": 1
    },
    {
        "lng": 110.3707,
        "lat": 20.027,
        "count": 1
    },
    {
        "lng": 110.3714,
        "lat": 19.9923,
        "count": 1
    },
    {
        "lng": 110.372,
        "lat": 20.0119,
        "count": 1
    },
    {
        "lng": 110.372,
        "lat": 20.0259,
        "count": 1
    },
    {
        "lng": 110.3721,
        "lat": 20.0119,
        "count": 1
    },
    {
        "lng": 110.3724,
        "lat": 20.0038,
        "count": 1
    },
    {
        "lng": 110.3725,
        "lat": 20.0042,
        "count": 1
    },
    {
        "lng": 110.3743,
        "lat": 20.0052,
        "count": 1
    },
    {
        "lng": 110.3743,
        "lat": 20.0297,
        "count": 1
    },
    {
        "lng": 110.3744,
        "lat": 19.9879,
        "count": 1
    },
    {
        "lng": 110.3748,
        "lat": 20.005,
        "count": 1
    },
    {
        "lng": 110.3748,
        "lat": 20.0216,
        "count": 1
    },
    {
        "lng": 110.3752,
        "lat": 20.0137,
        "count": 1
    },
    {
        "lng": 110.3753,
        "lat": 20.028,
        "count": 1
    },
    {
        "lng": 110.3765,
        "lat": 19.9894,
        "count": 1
    },
    {
        "lng": 110.3765,
        "lat": 19.9935,
        "count": 2
    },
    {
        "lng": 110.3765,
        "lat": 19.9966,
        "count": 1
    },
    {
        "lng": 110.3766,
        "lat": 20.0261,
        "count": 1
    },
    {
        "lng": 110.3766,
        "lat": 20.0262,
        "count": 1
    },
    {
        "lng": 110.3776,
        "lat": 20.0141,
        "count": 1
    },
    {
        "lng": 110.3785,
        "lat": 19.9953,
        "count": 1
    },
    {
        "lng": 110.3806,
        "lat": 19.9945,
        "count": 2
    },
    {
        "lng": 110.3808,
        "lat": 19.9945,
        "count": 1
    },
    {
        "lng": 110.3822,
        "lat": 19.9747,
        "count": 1
    },
    {
        "lng": 110.432,
        "lat": 19.952,
        "count": 1
    },
    {
        "lng": 110.4369,
        "lat": 19.9672,
        "count": 1
    },
    {
        "lng": 110.4392,
        "lat": 19.9643,
        "count": 1
    },
    {
        "lng": 110.4615,
        "lat": 19.9533,
        "count": 1
    },
    {
        "lng": 110.4625,
        "lat": 19.9397,
        "count": 1
    },
    {
        "lng": 110.4784,
        "lat": 19.9726,
        "count": 1
    }
]